{
    "건강" : [
    {"번호":"1","이미지":"1587705955249l0.jpg","상품명":"[올가비오] 사양벌꿀 1kg","정가":13900,"할인율":"0.05","후기이미지":"mention.svg","후기":999},
    {"번호":"2","이미지":"1565328879985l0.jpg","상품명":"[선물세트] 바로이즙 배도라지 진액 스틱 30포 +(쇼핑백 증정)","정가":27900,"할인율":"0.2","후기이미지":"mention.svg","후기":999},
    {"번호":"3","이미지":"783241ad-86c3-46bd-a03b-aed51f5aef7a.jpg","상품명":"[선물세트] 몸애쏙쏙 짜먹는 유기농 배도라지액 세트 +(쇼핑백 증정)","정가":39000,"할인율":"0.16","후기이미지":"mention.svg","후기":999},
    {"번호":"4","이미지":"9d9b1fcd-9ff4-41d5-a3a4-5e896b514051.jpg","상품명":"[올가비오] 곰돌이 아카시아꿀 프리미엄 (1+등급)","정가":21900,"할인율":"0.18","후기이미지":"mention.svg","후기":580},
    {"번호":"5","이미지":"279babaf-76d9-4d5d-8911-d1ac10c0a8da.jpg","상품명":"[제월당] 배도라지 진액 30포","정가":49000,"할인율":"0.41","후기이미지":"mention.svg","후기":37},
    {"번호":"6","이미지":"1637154300425l0.jpg","상품명":"[로트벡쉔] 11비타민 플러스 (7일분)","정가":19900,"할인율":"0.5","후기이미지":"mention.svg","후기":9999}
    ]
}